cookit/nonebot/__init__.py
cookit/nonebot/alconna.py
cookit_nonebot-0.1.0.dist-info/METADATA
cookit_nonebot-0.1.0.dist-info/WHEEL
cookit_nonebot-0.1.0.dist-info/licenses/LICENSE
cookit_nonebot-0.1.0.dist-info/RECORD
