Metadata-Version: 2.1
Name: cookit-nonebot
Version: 0.1.0
Summary: A NoneBot2 toolkit for self use.
Home-page: https://github.com/lgc-NB2Dev/cookit-nonebot
Author-Email: student_2333 <lgc2333@126.com>
License: MIT
Project-URL: Homepage, https://github.com/lgc-NB2Dev/cookit-nonebot
Requires-Python: <4.0,>=3.9
Requires-Dist: cookit>=0.0.0
Requires-Dist: nonebot2>=2.2.0
Requires-Dist: nonebot-plugin-alconna>=0.40.1; extra == "alconna"
Provides-Extra: alconna
